{
  "animateLoading": true,
  "bottomRow": 10,
  "capSide": 0,
  "capType": "nc",
  "dividerColor": "#324479",
  "dynamicBindingPathList": [],
  "dynamicTriggerPathList": [],
  "isLoading": false,
  "isVisible": true,
  "key": "kimaapercs",
  "leftColumn": 13,
  "minWidth": 450,
  "mobileBottomRow": 10,
  "mobileLeftColumn": 13,
  "mobileRightColumn": 33,
  "mobileTopRow": 6,
  "needsErrorInfo": false,
  "orientation": "horizontal",
  "parentColumnSpace": 16.8125,
  "parentId": "0",
  "parentRowSpace": 10,
  "renderMode": "CANVAS",
  "responsiveBehavior": "fill",
  "rightColumn": 64,
  "strokeStyle": "solid",
  "thickness": "2",
  "topRow": 6,
  "type": "DIVIDER_WIDGET",
  "version": 1,
  "widgetId": "4ss33vcxwi",
  "widgetName": "Divider2"
}