{
  "gitSyncId": "68f3f3e3241f5a3f1a6c0208_c6ae6dd3-bc86-4e1a-bfd8-901c528d0e97",
  "id": "Upload & Process_AuthHandler.logout",
  "pluginId": "js-plugin",
  "pluginType": "JS",
  "unpublishedAction": {
    "actionConfiguration": {
      "encodeParamsToggle": true,
      "jsArguments": [],
      "paginationType": "NONE",
      "timeoutInMillisecond": 10000
    },
    "collectionId": "Upload & Process_AuthHandler",
    "confirmBeforeExecute": false,
    "datasource": {
      "isAutoGenerated": false,
      "name": "UNUSED_DATASOURCE",
      "pluginId": "js-plugin"
    },
    "dynamicBindingPathList": [
      {
        "key": "body"
      }
    ],
    "fullyQualifiedName": "AuthHandler.logout",
    "name": "logout",
    "pageId": "Upload & Process",
    "runBehaviour": "MANUAL",
    "userSetOnLoad": false
  }
}