{
  "accentColor": "{{appsmith.theme.colors.primaryColor}}",
  "animateLoading": true,
  "borderRadius": "{{appsmith.theme.borderRadius.appBorderRadius}}",
  "bottomRow": 158,
  "boxShadow": "none",
  "capSide": 0,
  "capType": "nc",
  "displayName": "Divider",
  "dividerColor": "#5E6C9E",
  "dynamicBindingPathList": [
    {
      "key": "borderRadius"
    },
    {
      "key": "accentColor"
    }
  ],
  "dynamicTriggerPathList": [],
  "hideCard": false,
  "iconSVG": "/static/media/icon.cbe8f608ca868e1eb44607e5fbd4a9e5.svg",
  "isDeprecated": false,
  "isLoading": false,
  "isVisible": true,
  "key": "c3xzqeinqm",
  "leftColumn": 0,
  "orientation": "horizontal",
  "originalBottomRow": 93,
  "originalTopRow": 89,
  "parentColumnSpace": 3.7119140625,
  "parentId": "ae7ofn0j05",
  "parentRowSpace": 10,
  "renderMode": "CANVAS",
  "rightColumn": 64,
  "searchTags": [
    "line"
  ],
  "strokeStyle": "solid",
  "thickness": 2,
  "topRow": 154,
  "type": "DIVIDER_WIDGET",
  "version": 1,
  "widgetId": "s0kgb7ujxo",
  "widgetName": "Divider1"
}